<root>
	<window pos="0,0,-0,-0" skin="rich_file_bk">
		<img name="ImgFileIcon" pos="6,6,@36,@36" skin="sysiconlist" />
		<window name="LblFileName" align="left" font="size:12" pos="[4,4,-10,@22" />
		<text name="LblFileSize" font="size:12" colorText="#808080" pos="{0,[0,-10,@20"/>
		<hr pos="0,65,-0,66" size="1" colorLine="#ced9e2" />
		<text name="LblState" font="size:12" colorText="#808080" pos="10,[4,@100,@20"/>
		<window name="WndLinksContainer" pos="0,{0,-0,-0" >
			<link name="LnkOpenFile" pos="]-5,|0" offset="-1.0,-0.5" font="size:12" fontPush="underline:1,size:12" fontHover="underline:1,size:12" colorText="#1670eb" colorHover="#1670eb" display="0" visible="1">打开</link>
			<link name="LnkOpenFileDir" pos="]-5,|0" offset="-1.0,-0.5" font="size:12" fontPush="underline:1,size:12" fontHover="underline:1,size:12" colorText="#1670eb" colorHover="#1670eb" display="0" visible="1">打开文件夹</link>
			<link name="LnkContinueFile" pos="]-5,|0" offset="-1.0,-0.5" font="size:12" fontPush="underline:1,size:12" fontHover="underline:1,size:12" colorText="#1670eb" colorHover="#1670eb" display="0" visible="1">继续</link>
			<link name="LnkSaveFile" pos="]-5,|0" offset="-1.0,-0.5" font="size:12" fontPush="underline:1,size:12" fontHover="underline:1,size:12" colorText="#1670eb" colorHover="#1670eb" display="0" visible="1">保存</link>
			<link name="LnkSaveFileAs" pos="]-5,|0" offset="-1.0,-0.5" font="size:12" fontPush="underline:1,size:12" fontHover="underline:1,size:12" colorText="#1670eb" colorHover="#1670eb" display="0" visible="1" >下载</link>
			<link name="LnkCancelFile" pos="]-5,|0" offset="-1.0,-0.5" font="size:12" fontPush="underline:1,size:12" fontHover="underline:1,size:12" colorText="#1670eb" colorHover="#1670eb" display="0" visible="1">取消</link>
			<link name="LnkForwardFile" pos="]-5,|0" offset="-1.0,-0.5" font="size:12" fontPush="underline:1,size:12" fontHover="underline:1,size:12" colorText="#1670eb" colorHover="#1670eb" display="0" visible="1">转发</link>
		</window>
	</window>
</root>
