<include>
  <tabctrl pos="0,0,-0,-0" tabAlign="left" tabSkin="skin_tab_left" tabInterSkin="skin_tab_left_splitter" tabInterSize="2" tabWidth="200" iconSkin="skin_small_icons" icon-x="5" icon-y="8">
    <page title="script" colorBorder="#ff0000" margin-x="1" margin-y="1">
      <button name="btn_tstevt" pos="|-50,|-15,@100,@30" tip="click me to execute a lua script defined in lua\test.lua">script test</button>
    </page>
    <page title="drag drop">
      <edit name="edit_drop_top" pos="10,10,-10,]-10" cueText="draging a file to me to see what will happen"/>
      <text pos ="10,|0" offset="0,-0.5" colorText="RGB(255,0,0)"  colorBkgnd="RGB(0,255,0)">show how to implement dragdrop in soui</text>
      <edit name="edit_drop_bottom" pos="10,[10,-10,-10" cueText="draging a file to me to see what will happen"/>
    </page>
    <page title="animation" font="adding:10">
      <!--注意在uianimationwnd元素中指定bkgndBlend为0还是1对性能影响-->
      <uianimationwnd pos="0,0,-0,-0" icon="skin_small_icons" aniMode="imgx:png_animode"  colorBkgnd="#cccccc" bkgndBlend="0"/>
      <text pos="|0,20" offset="-0.5,0" colorText="#ff0000">SOUI动画演示</text>
    </page>
    <page title="flywnd">
      <window pos="0,0,-0,-0" clipClient="1" skin="skin_bkgnd" >
        <flywnd pos="-210,10,-0,-10" posEnd="-10,10,@210,-10" alpha="100" layeredWindow="1">
          <toggle pos="0,|-15,@10,@30" skin="skin_btn_expand" name="switch" cursor="hand" tip="click me to show the animator that show or hide the pane"></toggle>
          <window pos="10,0,-0,-0" colorBkgnd="#ff0000">
            <treectrl pos="10,0,-10,-10"  name="mytree2" itemHeight="30" iconSkin="skin_tree_icon" checkBox="1" font="underline:1">
              <item text="组织机构" img="0" selImg="1"  expand="0">
                <item text="市场部" img="0" selImg="1">
                  <item text="南一区" img="2"/>
                  <item text="北二区" img="2"/>
                  <item text="西三区" img="2">
                    <item text="第一分队" img="0" selImg="1" expand="0">
                      <item text="张三组" img="2"/>
                      <item text="李四组" img="2"/>
                      <item text="王五组" img="2"/>
                    </item>
                  </item>
                </item>
              </item>
              <item text="宣传部" img="0" selImg="1" expand="0">
                <item text="南一区" img="2"/>
                <item text="北二区" img="2"/>
                <item text="西三区" img="2"/>
              </item>
            </treectrl>

            <text pos="10,-100,-0,@100" multilines="1">click the left grip to \nshow or hide the \npane</text>
          </window>
        </flywnd>
      </window>
    </page>
  </tabctrl>
</include>
